exec_cmds_defer_errors/__init__.py
exec_cmds_defer_errors/exec_cmds_defer_errors.py
exec_cmds_defer_errors/py.typed
exec_cmds_defer_errors-2.1.1.dist-info/METADATA
exec_cmds_defer_errors-2.1.1.dist-info/WHEEL
exec_cmds_defer_errors-2.1.1.dist-info/entry_points.txt
exec_cmds_defer_errors-2.1.1.dist-info/licenses/LICENSE
exec_cmds_defer_errors-2.1.1.dist-info/RECORD
