Metadata-Version: 2.4
Name: exec-cmds-defer-errors
Version: 2.1.1
Project-URL: Homepage, https://github.com/trallnag/exec-cmds-defer-errors
Project-URL: Documentation, https://github.com/trallnag/exec-cmds-defer-errors
Project-URL: Repository, https://github.com/trallnag/exec-cmds-defer-errors.git
Project-URL: Issues, https://github.com/trallnag/exec-cmds-defer-errors/issues
Project-URL: Changelog, https://github.com/trallnag/exec-cmds-defer-errors/blob/master/CHANGELOG.md
Author-email: Tim Schwenke <tim@trallnag.com>
License-Expression: ISC
License-File: LICENSE
Requires-Python: >=3.12
Requires-Dist: click==8.1.8
